{
    "routine": [
      {
        "id": 1,
        "date": "2023.04.05",
        "title": "크런치 (crunch)",
        "set": "30개 / 2 set",
        "isDone": false
      },
      {
        "id": 2,
        "date": "2023.04.05",
        "title": "크런치 (crunch)",
        "kor": "30개 / 2 set",
        "isDone": false
      },
      {
        "id": 3,
        "date": "2023.04.05",
        "title": "크런치 (crunch)",
        "kor": "30개 / 2 set",
        "isDone": false
      },
      {
        "id": 4,
        "date": "2023.04.05",
        "title": "크런치 (crunch)",
        "set": "30개 / 2 set",
        "isDone": false
      },
      {
        "id": 5,
        "date": "2023.04.05",
        "title": "크런치 (crunch)",
        "kor": "30개 / 2 set",
        "isDone": false
      },
      {
        "id": 6,
        "date": "2023.04.05",
        "title": "크런치 (crunch)",
        "kor": "30개 / 2 set",
        "isDone": false
      },
      {
        "id": 7,
        "date": "2023.04.05",
        "title": "크런치 (crunch)",
        "set": "30개 / 2 set",
        "isDone": false
      },
      {
        "id": 8,
        "date": "2023.04.05",
        "title": "크런치 (crunch)",
        "kor": "30개 / 2 set",
        "isDone": false
      },
      {
        "id": 9,
        "date": "2023.04.05",
        "title": "크런치 (crunch)",
        "kor": "30개 / 2 set",
        "isDone": false
      }
    ]
    ,
    "ranking": [
      {
        "id": 1,
        "ranking": 1,
        "nickname": "kimyerim",
        "time": "0130",
        "score": 73,
        "kcal":150,
        "attend":100,
        "profile":"https://www.google.com/url?sa=i&url=https%3A%2F%2Fpixabay.com%2Fvectors%2Fblank-profile-picture-mystery-man-973460%2F&psig=AOvVaw0z9PGxv-bPFqQRSOL-1KoA&ust=1680859092880000&source=images&cd=vfe&ved=0CBAQjRxqFwoTCKiMvZv2lP4CFQAAAAAdAAAAABAD"
      },
      {
        "id": 2,
        "ranking": 2,
        "nickname": "kimyerim",
        "time": "0130",
        "score": 73,
        "kcal":150,
        "attend":100,
        "profile":"https://www.google.com/url?sa=i&url=https%3A%2F%2Fpixabay.com%2Fvectors%2Fblank-profile-picture-mystery-man-973460%2F&psig=AOvVaw0z9PGxv-bPFqQRSOL-1KoA&ust=1680859092880000&source=images&cd=vfe&ved=0CBAQjRxqFwoTCKiMvZv2lP4CFQAAAAAdAAAAABAD"
      },
      {
        "id": 3,
        "ranking": 3,
        "nickname": "kimyerim",
        "time": "0130",
        "score": 73,
        "kcal":150,
        "attend":100,
        "profile":"https://www.google.com/url?sa=i&url=https%3A%2F%2Fpixabay.com%2Fvectors%2Fblank-profile-picture-mystery-man-973460%2F&psig=AOvVaw0z9PGxv-bPFqQRSOL-1KoA&ust=1680859092880000&source=images&cd=vfe&ved=0CBAQjRxqFwoTCKiMvZv2lP4CFQAAAAAdAAAAABAD"
      },
      {
        "id": 4,
        "ranking": 4,
        "nickname": "kimyerim",
        "time": "0130",
        "score": 73,
        "kcal":150,
        "attend":100,
        "profile":"https://www.google.com/url?sa=i&url=https%3A%2F%2Fpixabay.com%2Fvectors%2Fblank-profile-picture-mystery-man-973460%2F&psig=AOvVaw0z9PGxv-bPFqQRSOL-1KoA&ust=1680859092880000&source=images&cd=vfe&ved=0CBAQjRxqFwoTCKiMvZv2lP4CFQAAAAAdAAAAABAD"
      },
      {
        "id": 5,
        "ranking": 5,
        "nickname": "kimyerim",
        "time": "0130",
        "score": 73,
        "kcal":150,
        "attend":100,
        "profile":"https://www.google.com/url?sa=i&url=https%3A%2F%2Fpixabay.com%2Fvectors%2Fblank-profile-picture-mystery-man-973460%2F&psig=AOvVaw0z9PGxv-bPFqQRSOL-1KoA&ust=1680859092880000&source=images&cd=vfe&ved=0CBAQjRxqFwoTCKiMvZv2lP4CFQAAAAAdAAAAABAD"
      },
      {
        "id": 6,
        "ranking": 6,
        "nickname": "kimyerim",
        "time": "0130",
        "score": 73,
        "kcal":150,
        "attend":100,
        "profile":"https://www.google.com/url?sa=i&url=https%3A%2F%2Fpixabay.com%2Fvectors%2Fblank-profile-picture-mystery-man-973460%2F&psig=AOvVaw0z9PGxv-bPFqQRSOL-1KoA&ust=1680859092880000&source=images&cd=vfe&ved=0CBAQjRxqFwoTCKiMvZv2lP4CFQAAAAAdAAAAABAD"
      },
      {
        "id": 7,
        "ranking": 7,
        "nickname": "kimyerim",
        "time": "0130",
        "score": 73,
        "kcal":150,
        "attend":100,
        "profile":"https://www.google.com/url?sa=i&url=https%3A%2F%2Fpixabay.com%2Fvectors%2Fblank-profile-picture-mystery-man-973460%2F&psig=AOvVaw0z9PGxv-bPFqQRSOL-1KoA&ust=1680859092880000&source=images&cd=vfe&ved=0CBAQjRxqFwoTCKiMvZv2lP4CFQAAAAAdAAAAABAD"
      },
      {
        "id": 8,
        "ranking": 8,
        "nickname": "kimyerim",
        "time": "0130",
        "score": 73,
        "kcal":150,
        "attend":100,
        "profile":"https://www.google.com/url?sa=i&url=https%3A%2F%2Fpixabay.com%2Fvectors%2Fblank-profile-picture-mystery-man-973460%2F&psig=AOvVaw0z9PGxv-bPFqQRSOL-1KoA&ust=1680859092880000&source=images&cd=vfe&ved=0CBAQjRxqFwoTCKiMvZv2lP4CFQAAAAAdAAAAABAD"
      },
      {
        "id": 9,
        "ranking": 9,
        "nickname": "kimyerim",
        "time": "0130",
        "score": 73,
        "kcal":150,
        "attend":100,
        "profile":"https://www.google.com/url?sa=i&url=https%3A%2F%2Fpixabay.com%2Fvectors%2Fblank-profile-picture-mystery-man-973460%2F&psig=AOvVaw0z9PGxv-bPFqQRSOL-1KoA&ust=1680859092880000&source=images&cd=vfe&ved=0CBAQjRxqFwoTCKiMvZv2lP4CFQAAAAAdAAAAABAD"
      },
      {
        "id": 10,
        "ranking": 10,
        "nickname": "kimyerim",
        "time": "0130",
        "score": 73,
        "kcal":150,
        "attend":100,
        "profile":"https://www.google.com/url?sa=i&url=https%3A%2F%2Fpixabay.com%2Fvectors%2Fblank-profile-picture-mystery-man-973460%2F&psig=AOvVaw0z9PGxv-bPFqQRSOL-1KoA&ust=1680859092880000&source=images&cd=vfe&ved=0CBAQjRxqFwoTCKiMvZv2lP4CFQAAAAAdAAAAABAD"
      },
      {
        "id": 11,
        "ranking": 11,
        "nickname": "kimyerim",
        "time": "0130",
        "score": 73,
        "kcal":150,
        "attend":100,
        "profile":"https://www.google.com/url?sa=i&url=https%3A%2F%2Fpixabay.com%2Fvectors%2Fblank-profile-picture-mystery-man-973460%2F&psig=AOvVaw0z9PGxv-bPFqQRSOL-1KoA&ust=1680859092880000&source=images&cd=vfe&ved=0CBAQjRxqFwoTCKiMvZv2lP4CFQAAAAAdAAAAABAD"
      },
      {
        "id":12,
        "ranking": 12,
        "nickname": "kimyerim",
        "time": "0130",
        "score": 73,
        "kcal":150,
        "attend":100,
        "profile":"https://www.google.com/url?sa=i&url=https%3A%2F%2Fpixabay.com%2Fvectors%2Fblank-profile-picture-mystery-man-973460%2F&psig=AOvVaw0z9PGxv-bPFqQRSOL-1KoA&ust=1680859092880000&source=images&cd=vfe&ved=0CBAQjRxqFwoTCKiMvZv2lP4CFQAAAAAdAAAAABAD"
      },
      {
        "id": 13,
        "ranking": 13,
        "nickname": "kimyerim",
        "time": "0130",
        "score": 73,
        "kcal":150,
        "attend":100,
        "profile":"https://www.google.com/url?sa=i&url=https%3A%2F%2Fpixabay.com%2Fvectors%2Fblank-profile-picture-mystery-man-973460%2F&psig=AOvVaw0z9PGxv-bPFqQRSOL-1KoA&ust=1680859092880000&source=images&cd=vfe&ved=0CBAQjRxqFwoTCKiMvZv2lP4CFQAAAAAdAAAAABAD"
      }
    ]
  }